CBCgrpspy/CBCgrpspy.py
CBCgrpspy/__init__.py
cbcgrpspy-0.4.dist-info/METADATA
cbcgrpspy-0.4.dist-info/WHEEL
cbcgrpspy-0.4.dist-info/top_level.txt
cbcgrpspy-0.4.dist-info/RECORD
