Metadata-Version: 2.4
Name: CBCgrpspy
Version: 0.4
Summary: Statistical Group Comparison Tool
Home-page: https://github.com/Jarrily
Author: Jinhui Liu
Author-email: ljh18620847741@gmail.com
Classifier: Topic :: Scientific/Engineering :: Medical Science Apps.
Classifier: Intended Audience :: Science/Research
Classifier: Programming Language :: Python :: 3.10
Classifier: License :: OSI Approved :: MIT License
Classifier: Operating System :: Microsoft :: Windows :: Windows 11
Requires-Python: ~=3.10
Requires-Dist: numpy==1.26.4
Requires-Dist: pandas
Requires-Dist: scipy
Requires-Dist: openpyxl
Dynamic: author
Dynamic: author-email
Dynamic: classifier
Dynamic: description
Dynamic: description-content-type
Dynamic: home-page
Dynamic: requires-dist
Dynamic: requires-python
Dynamic: summary
